netbox_proxbox_new/__init__.py
netbox_proxbox_new/admin.py
netbox_proxbox_new/api/serializers.py
netbox_proxbox_new/api/urls.py
netbox_proxbox_new/api/views.py
netbox_proxbox_new/filters.py
netbox_proxbox_new/forms.py
netbox_proxbox_new/icon_classes.py
netbox_proxbox_new/migrations/0001_initial.py
netbox_proxbox_new/migrations/0002_vmresources_description.py
netbox_proxbox_new/migrations/0003_auto_20210419_2330.py
netbox_proxbox_new/migrations/__init__.py
netbox_proxbox_new/models.py
netbox_proxbox_new/navigation.py
netbox_proxbox_new/proxbox_api/README.md
netbox_proxbox_new/proxbox_api/__init__.py
netbox_proxbox_new/proxbox_api/create.py
netbox_proxbox_new/proxbox_api/main.py
netbox_proxbox_new/proxbox_api/remove.py
netbox_proxbox_new/proxbox_api/updates.py
netbox_proxbox_new/release.py
netbox_proxbox_new/tables.py
netbox_proxbox_new/template_content.py
netbox_proxbox_new/templates/netbox_proxbox/proxmox_vm.html
netbox_proxbox_new/templates/netbox_proxbox/proxmox_vm_delete.html
netbox_proxbox_new/templates/netbox_proxbox/proxmox_vm_edit.html
netbox_proxbox_new/templates/netbox_proxbox/proxmox_vm_full_update.html
netbox_proxbox_new/templates/netbox_proxbox/proxmox_vm_list.html
netbox_proxbox_new/templates/netbox_proxbox/virtualmachine_proxmox_fields.html
netbox_proxbox_new/urls.py
netbox_proxbox_new/views.py
netbox_proxbox_new-0.0.0.1.dist-info/LICENSE
netbox_proxbox_new-0.0.0.1.dist-info/WHEEL
netbox_proxbox_new-0.0.0.1.dist-info/METADATA
netbox_proxbox_new-0.0.0.1.dist-info/RECORD
