Metadata-Version: 2.1
Name: netbox-proxbox-new
Version: 0.0.0.1
Summary: Netbox Plugin - Integrate Proxmox and Netbox
License: Apache-2.0
Author: Sebastian Winkelmann
Author-email: sebastian.winkelmann@check24.de
Requires-Python: >=3.8,<4.0
Classifier: License :: OSI Approved :: Apache Software License
Classifier: Programming Language :: Python :: 3
Classifier: Programming Language :: Python :: 3.10
Classifier: Programming Language :: Python :: 3.8
Classifier: Programming Language :: Python :: 3.9
